{
  "job": "szrcr.cz_activni_osoby",
  "parser": {
    "kind": "csv",
    "options": {
      "comma": ",",
      "expected_fields": 24,
      "has_header": true,
      "header_map": {
        "AGENDA": "agenda",
        "DAPSČ": "daps",
        "DARUIAN": "daruian",
        "DATEXT": "datext",
        "DATPLAT": "datplat",
        "DATVZN": "datvzn",
        "DATZAN": "datzan",
        "DATZAP": "datzap",
        "DATZMĚN": "datzmn",
        "FIRMA": "firma",
        "FORMA": "forma",
        "ICO": "ico",
        "INS": "ins",
        "KODADM": "kodadm",
        "LIKV": "likv",
        "NS": "ns",
        "OPAT": "opat",
        "OVM": "ovm",
        "PRERUSENI": "preruseni",
        "PROV": "prov",
        "STAT": "stat",
        "STAV": "stav",
        "TEXTADR": "textadr",
        "ZASTFO": "zastfo"
      },
      "trim_space": true
    }
  },
  "runtime": {
    "batch_size": 2048,
    "channel_buffer": 512,
    "dedupe_dimension_keys": false,
    "dedupe_dimension_keys_within_batch": false,
    "loader_workers": 2,
    "reader_workers": 1,
    "transform_workers": 2,
    "validate_log_first_n": 25
  },
  "source": {
    "file": {
      "path": "/data/activni_osoby.csv"
    },
    "kind": "file"
  },
  "storage": {
    "db": {
      "dsn": "postgresql://user:password@0.0.0.0:5432/testdb?sslmode=disable",
      "mode": "multi_table",
      "tables": [
        {
          "auto_create_table": true,
          "columns": [
            {
              "name": "row_hash",
              "nullable": false,
              "type": "text"
            },
            {
              "name": "ico",
              "nullable": false,
              "type": "text"
            },
            {
              "name": "valid_from",
              "nullable": false,
              "type": "timestamptz"
            },
            {
              "name": "valid_to",
              "nullable": true,
              "type": "timestamptz"
            },
            {
              "name": "changed_at",
              "nullable": false,
              "type": "timestamptz"
            },
            {
              "name": "agenda",
              "nullable": true,
              "type": "text"
            },
            {
              "name": "firma",
              "nullable": true,
              "type": "text"
            },
            {
              "name": "stav",
              "nullable": true,
              "type": "bigint"
            },
            {
              "name": "forma",
              "nullable": true,
              "type": "bigint"
            },
            {
              "name": "kodadm",
              "nullable": true,
              "type": "text"
            },
            {
              "name": "textadr",
              "nullable": true,
              "type": "text"
            },
            {
              "name": "stat",
              "nullable": true,
              "type": "bigint"
            },
            {
              "name": "likv",
              "nullable": true,
              "type": "bigint"
            },
            {
              "name": "opat",
              "nullable": true,
              "type": "bigint"
            },
            {
              "name": "ins",
              "nullable": true,
              "type": "bigint"
            },
            {
              "name": "ns",
              "nullable": true,
              "type": "bigint"
            },
            {
              "name": "zastfo",
              "nullable": true,
              "type": "bigint"
            },
            {
              "name": "prov",
              "nullable": true,
              "type": "bigint"
            },
            {
              "name": "datvzn",
              "nullable": true,
              "type": "date"
            },
            {
              "name": "datzan",
              "nullable": true,
              "type": "date"
            },
            {
              "name": "preruseni",
              "nullable": true,
              "type": "bigint"
            },
            {
              "name": "daruian",
              "nullable": true,
              "type": "text"
            },
            {
              "name": "datext",
              "nullable": true,
              "type": "text"
            },
            {
              "name": "daps",
              "nullable": true,
              "type": "text"
            },
            {
              "name": "ovm",
              "nullable": true,
              "type": "text"
            },
            {
              "name": "datzap",
              "nullable": true,
              "type": "date"
            },
            {
              "name": "datzmn",
              "nullable": true,
              "type": "date"
            },
            {
              "name": "datplat",
              "nullable": true,
              "type": "date"
            }
          ],
          "constraints": [
            {
              "columns": [
                "ico"
              ],
              "kind": "unique"
            }
          ],
          "load": {
            "dedupe": {
              "action": "do_nothing",
              "conflict_columns": [
                "ico"
              ]
            },
            "from_rows": [
              {
                "source_field": "row_hash",
                "target_column": "row_hash"
              },
              {
                "source_field": "ico",
                "target_column": "ico"
              },
              {
                "source_field": "agenda",
                "target_column": "agenda"
              },
              {
                "source_field": "firma",
                "target_column": "firma"
              },
              {
                "source_field": "stav",
                "target_column": "stav"
              },
              {
                "source_field": "forma",
                "target_column": "forma"
              },
              {
                "source_field": "kodadm",
                "target_column": "kodadm"
              },
              {
                "source_field": "textadr",
                "target_column": "textadr"
              },
              {
                "source_field": "stat",
                "target_column": "stat"
              },
              {
                "source_field": "likv",
                "target_column": "likv"
              },
              {
                "source_field": "opat",
                "target_column": "opat"
              },
              {
                "source_field": "ins",
                "target_column": "ins"
              },
              {
                "source_field": "ns",
                "target_column": "ns"
              },
              {
                "source_field": "zastfo",
                "target_column": "zastfo"
              },
              {
                "source_field": "prov",
                "target_column": "prov"
              },
              {
                "source_field": "datvzn",
                "target_column": "datvzn"
              },
              {
                "source_field": "datzan",
                "target_column": "datzan"
              },
              {
                "source_field": "preruseni",
                "target_column": "preruseni"
              },
              {
                "source_field": "daruian",
                "target_column": "daruian"
              },
              {
                "source_field": "datext",
                "target_column": "datext"
              },
              {
                "source_field": "daps",
                "target_column": "daps"
              },
              {
                "source_field": "ovm",
                "target_column": "ovm"
              },
              {
                "source_field": "datzap",
                "target_column": "datzap"
              },
              {
                "source_field": "datzmn",
                "target_column": "datzmn"
              },
              {
                "source_field": "datplat",
                "target_column": "datplat"
              }
            ],
            "history": {
              "business_key": [
                "ico"
              ],
              "changed_at_column": "changed_at",
              "enabled": true,
              "valid_from_column": "valid_from",
              "valid_to_column": "valid_to"
            },
            "kind": "fact"
          },
          "name": "public.ros01_activni_osoby",
          "primary_key": {
            "name": "ros01_activni_osoby_id",
            "type": "serial"
          }
        }
      ]
    },
    "kind": "postgres"
  },
  "transform": [
    {
      "kind": "coerce",
      "options": {
        "layout": "2006-01-02",
        "types": {
          "datplat": "date",
          "datvzn": "date",
          "datzan": "date",
          "datzap": "date",
          "datzmn": "date",
          "forma": "bigint",
          "ins": "bigint",
          "likv": "bigint",
          "ns": "bigint",
          "opat": "bigint",
          "preruseni": "bigint",
          "prov": "bigint",
          "stat": "bigint",
          "stav": "bigint",
          "zastfo": "bigint"
        }
      }
    },
    {
      "kind": "hash",
      "options": {
        "algorithm": "sha256",
        "encoding": "hex",
        "fields": [
          "ico",
          "agenda",
          "firma",
          "stav",
          "forma",
          "kodadm",
          "textadr",
          "stat",
          "likv",
          "opat",
          "ins",
          "ns",
          "zastfo",
          "prov",
          "datvzn",
          "datzan",
          "preruseni",
          "daruian",
          "datext",
          "daps",
          "ovm",
          "datzap",
          "datzmn",
          "datplat"
        ],
        "include_field_names": true,
        "overwrite": true,
        "separator": "\u001f",
        "target_field": "row_hash",
        "trim_space": true
      }
    },
    {
      "kind": "validate",
      "options": {
        "contract": {
          "fields": [
            {
              "name": "ico",
              "required": true,
              "type": "text"
            },
            {
              "name": "agenda",
              "type": "text"
            },
            {
              "name": "firma",
              "type": "text"
            },
            {
              "name": "stav",
              "type": "bigint"
            },
            {
              "name": "forma",
              "type": "bigint"
            },
            {
              "name": "kodadm",
              "type": "text"
            },
            {
              "name": "textadr",
              "type": "text"
            },
            {
              "name": "stat",
              "type": "bigint"
            },
            {
              "name": "likv",
              "type": "bigint"
            },
            {
              "name": "opat",
              "type": "bigint"
            },
            {
              "name": "ins",
              "type": "bigint"
            },
            {
              "name": "ns",
              "type": "bigint"
            },
            {
              "name": "zastfo",
              "type": "bigint"
            },
            {
              "name": "prov",
              "type": "bigint"
            },
            {
              "layout": "2006-01-02",
              "name": "datvzn",
              "type": "date"
            },
            {
              "layout": "2006-01-02",
              "name": "datzan",
              "type": "date"
            },
            {
              "name": "preruseni",
              "type": "bigint"
            },
            {
              "name": "daruian",
              "type": "text"
            },
            {
              "name": "datext",
              "type": "text"
            },
            {
              "name": "daps",
              "type": "text"
            },
            {
              "name": "ovm",
              "type": "text"
            },
            {
              "layout": "2006-01-02",
              "name": "datzap",
              "type": "date"
            },
            {
              "layout": "2006-01-02",
              "name": "datzmn",
              "type": "date"
            },
            {
              "layout": "2006-01-02",
              "name": "datplat",
              "type": "date"
            },
            {
              "name": "row_hash",
              "required": true,
              "type": "text"
            }
          ],
          "name": "ros01_activni_osoby"
        },
        "policy": "lenient"
      }
    }
  ]
}
